<annotation>
  <object>
    <name>Vehicle</name>
    <bndbox>
      <xmin>784</xmin>
      <ymin>533</ymin>
      <xmax>811</xmax>
      <ymax>559</ymax>
    </bndbox>
    <confidence>0.011261</confidence>
  </object>
  <object>
    <name>Pedestrian</name>
    <bndbox>
      <xmin>615</xmin>
      <ymin>538</ymin>
      <xmax>628</xmax>
      <ymax>561</ymax>
    </bndbox>
    <confidence>0.0141449</confidence>
  </object>
  <object>
    <name>Vehicle</name>
    <bndbox>
      <xmin>927</xmin>
      <ymin>534</ymin>
      <xmax>963</xmax>
      <ymax>554</ymax>
    </bndbox>
    <confidence>0.0143814</confidence>
  </object>
  <object>
    <name>TrafficLight</name>
    <bndbox>
      <xmin>689</xmin>
      <ymin>453</ymin>
      <xmax>704</xmax>
      <ymax>459</ymax>
    </bndbox>
    <confidence>0.0158844</confidence>
  </object>
  <object>
    <name>Vehicle</name>
    <bndbox>
      <xmin>791</xmin>
      <ymin>532</ymin>
      <xmax>830</xmax>
      <ymax>562</ymax>
    </bndbox>
    <confidence>0.0170441</confidence>
  </object>
  <object>
    <name>Vehicle</name>
    <bndbox>
      <xmin>613</xmin>
      <ymin>527</ymin>
      <xmax>673</xmax>
      <ymax>558</ymax>
    </bndbox>
    <confidence>0.0189056</confidence>
  </object>
  <object>
    <name>Pedestrian</name>
    <bndbox>
      <xmin>975</xmin>
      <ymin>534</ymin>
      <xmax>988</xmax>
      <ymax>558</ymax>
    </bndbox>
    <confidence>0.0191956</confidence>
  </object>
  <object>
    <name>TrafficLight</name>
    <bndbox>
      <xmin>591</xmin>
      <ymin>495</ymin>
      <xmax>608</xmax>
      <ymax>501</ymax>
    </bndbox>
    <confidence>0.0261688</confidence>
  </object>
  <object>
    <name>Vehicle</name>
    <bndbox>
      <xmin>827</xmin>
      <ymin>521</ymin>
      <xmax>854</xmax>
      <ymax>552</ymax>
    </bndbox>
    <confidence>0.0487061</confidence>
  </object>
  <object>
    <name>Vehicle</name>
    <bndbox>
      <xmin>711</xmin>
      <ymin>519</ymin>
      <xmax>736</xmax>
      <ymax>556</ymax>
    </bndbox>
    <confidence>0.0637817</confidence>
  </object>
  <object>
    <name>Vehicle</name>
    <bndbox>
      <xmin>730</xmin>
      <ymin>535</ymin>
      <xmax>759</xmax>
      <ymax>557</ymax>
    </bndbox>
    <confidence>0.0733032</confidence>
  </object>
  <object>
    <name>Vehicle</name>
    <bndbox>
      <xmin>914</xmin>
      <ymin>526</ymin>
      <xmax>952</xmax>
      <ymax>553</ymax>
    </bndbox>
    <confidence>0.0857544</confidence>
  </object>
  <object>
    <name>Vehicle</name>
    <bndbox>
      <xmin>404</xmin>
      <ymin>537</ymin>
      <xmax>449</xmax>
      <ymax>562</ymax>
    </bndbox>
    <confidence>0.783691</confidence>
  </object>
  <object>
    <name>Vehicle</name>
    <bndbox>
      <xmin>730</xmin>
      <ymin>535</ymin>
      <xmax>759</xmax>
      <ymax>557</ymax>
    </bndbox>
    <confidence>0.808594</confidence>
  </object>
  <object>
    <name>Vehicle</name>
    <bndbox>
      <xmin>929</xmin>
      <ymin>495</ymin>
      <xmax>994</xmax>
      <ymax>553</ymax>
    </bndbox>
    <confidence>0.831543</confidence>
  </object>
  <object>
    <name>Vehicle</name>
    <bndbox>
      <xmin>865</xmin>
      <ymin>514</ymin>
      <xmax>898</xmax>
      <ymax>552</ymax>
    </bndbox>
    <confidence>0.881348</confidence>
  </object>
  <object>
    <name>Vehicle</name>
    <bndbox>
      <xmin>791</xmin>
      <ymin>532</ymin>
      <xmax>831</xmax>
      <ymax>562</ymax>
    </bndbox>
    <confidence>0.892578</confidence>
  </object>
  <object>
    <name>Vehicle</name>
    <bndbox>
      <xmin>1024</xmin>
      <ymin>498</ymin>
      <xmax>1135</xmax>
      <ymax>565</ymax>
    </bndbox>
    <confidence>0.924805</confidence>
  </object>
  <object>
    <name>Vehicle</name>
    <bndbox>
      <xmin>1</xmin>
      <ymin>537</ymin>
      <xmax>94</xmax>
      <ymax>634</ymax>
    </bndbox>
    <confidence>0.938965</confidence>
  </object>
</annotation>
