<annotation>
  <object>
    <name>Vehicle</name>
    <bndbox>
      <xmin>925</xmin>
      <ymin>526</ymin>
      <xmax>951</xmax>
      <ymax>547</ymax>
    </bndbox>
    <confidence>0.0128632</confidence>
  </object>
  <object>
    <name>Vehicle</name>
    <bndbox>
      <xmin>916</xmin>
      <ymin>524</ymin>
      <xmax>939</xmax>
      <ymax>544</ymax>
    </bndbox>
    <confidence>0.111877</confidence>
  </object>
  <object>
    <name>Vehicle</name>
    <bndbox>
      <xmin>925</xmin>
      <ymin>526</ymin>
      <xmax>951</xmax>
      <ymax>547</ymax>
    </bndbox>
    <confidence>0.692383</confidence>
  </object>
  <object>
    <name>Vehicle</name>
    <bndbox>
      <xmin>869</xmin>
      <ymin>526</ymin>
      <xmax>904</xmax>
      <ymax>555</ymax>
    </bndbox>
    <confidence>0.904297</confidence>
  </object>
  <object>
    <name>Vehicle</name>
    <bndbox>
      <xmin>298</xmin>
      <ymin>446</ymin>
      <xmax>534</xmax>
      <ymax>582</ymax>
    </bndbox>
    <confidence>0.937012</confidence>
  </object>
  <object>
    <name>Vehicle</name>
    <bndbox>
      <xmin>768</xmin>
      <ymin>516</ymin>
      <xmax>864</xmax>
      <ymax>593</ymax>
    </bndbox>
    <confidence>0.95166</confidence>
  </object>
  <object>
    <name>Vehicle</name>
    <bndbox>
      <xmin>1059</xmin>
      <ymin>502</ymin>
      <xmax>1174</xmax>
      <ymax>593</ymax>
    </bndbox>
    <confidence>0.952637</confidence>
  </object>
</annotation>
