<annotation>
  <object>
    <name>Vehicle</name>
    <bndbox>
      <xmin>1722</xmin>
      <ymin>381</ymin>
      <xmax>1765</xmax>
      <ymax>428</ymax>
    </bndbox>
    <confidence>0.0102844</confidence>
  </object>
  <object>
    <name>Vehicle</name>
    <bndbox>
      <xmin>927</xmin>
      <ymin>511</ymin>
      <xmax>1011</xmax>
      <ymax>601</ymax>
    </bndbox>
    <confidence>0.0115128</confidence>
  </object>
  <object>
    <name>Vehicle</name>
    <bndbox>
      <xmin>1463</xmin>
      <ymin>423</ymin>
      <xmax>1548</xmax>
      <ymax>472</ymax>
    </bndbox>
    <confidence>0.0125122</confidence>
  </object>
  <object>
    <name>Vehicle</name>
    <bndbox>
      <xmin>1030</xmin>
      <ymin>538</ymin>
      <xmax>1048</xmax>
      <ymax>554</ymax>
    </bndbox>
    <confidence>0.0137558</confidence>
  </object>
  <object>
    <name>Vehicle</name>
    <bndbox>
      <xmin>1694</xmin>
      <ymin>375</ymin>
      <xmax>1764</xmax>
      <ymax>439</ymax>
    </bndbox>
    <confidence>0.0143356</confidence>
  </object>
  <object>
    <name>Vehicle</name>
    <bndbox>
      <xmin>1494</xmin>
      <ymin>423</ymin>
      <xmax>1554</xmax>
      <ymax>454</ymax>
    </bndbox>
    <confidence>0.0159607</confidence>
  </object>
  <object>
    <name>Vehicle</name>
    <bndbox>
      <xmin>1608</xmin>
      <ymin>376</ymin>
      <xmax>1763</xmax>
      <ymax>450</ymax>
    </bndbox>
    <confidence>0.0192719</confidence>
  </object>
  <object>
    <name>Vehicle</name>
    <bndbox>
      <xmin>1674</xmin>
      <ymin>398</ymin>
      <xmax>1746</xmax>
      <ymax>447</ymax>
    </bndbox>
    <confidence>0.0198822</confidence>
  </object>
  <object>
    <name>Vehicle</name>
    <bndbox>
      <xmin>1674</xmin>
      <ymin>398</ymin>
      <xmax>1746</xmax>
      <ymax>447</ymax>
    </bndbox>
    <confidence>0.0218964</confidence>
  </object>
  <object>
    <name>Vehicle</name>
    <bndbox>
      <xmin>1687</xmin>
      <ymin>420</ymin>
      <xmax>1729</xmax>
      <ymax>447</ymax>
    </bndbox>
    <confidence>0.0243225</confidence>
  </object>
  <object>
    <name>Vehicle</name>
    <bndbox>
      <xmin>918</xmin>
      <ymin>528</ymin>
      <xmax>936</xmax>
      <ymax>558</ymax>
    </bndbox>
    <confidence>0.0259857</confidence>
  </object>
  <object>
    <name>Vehicle</name>
    <bndbox>
      <xmin>1690</xmin>
      <ymin>376</ymin>
      <xmax>1765</xmax>
      <ymax>438</ymax>
    </bndbox>
    <confidence>0.0260773</confidence>
  </object>
  <object>
    <name>Vehicle</name>
    <bndbox>
      <xmin>691</xmin>
      <ymin>525</ymin>
      <xmax>720</xmax>
      <ymax>541</ymax>
    </bndbox>
    <confidence>0.0290985</confidence>
  </object>
  <object>
    <name>Vehicle</name>
    <bndbox>
      <xmin>1552</xmin>
      <ymin>393</ymin>
      <xmax>1639</xmax>
      <ymax>466</ymax>
    </bndbox>
    <confidence>0.0292206</confidence>
  </object>
  <object>
    <name>Vehicle</name>
    <bndbox>
      <xmin>1030</xmin>
      <ymin>538</ymin>
      <xmax>1048</xmax>
      <ymax>554</ymax>
    </bndbox>
    <confidence>0.0313416</confidence>
  </object>
  <object>
    <name>Vehicle</name>
    <bndbox>
      <xmin>1701</xmin>
      <ymin>374</ymin>
      <xmax>1759</xmax>
      <ymax>398</ymax>
    </bndbox>
    <confidence>0.0335999</confidence>
  </object>
  <object>
    <name>Vehicle</name>
    <bndbox>
      <xmin>691</xmin>
      <ymin>527</ymin>
      <xmax>720</xmax>
      <ymax>541</ymax>
    </bndbox>
    <confidence>0.0476074</confidence>
  </object>
  <object>
    <name>Vehicle</name>
    <bndbox>
      <xmin>1699</xmin>
      <ymin>373</ymin>
      <xmax>1761</xmax>
      <ymax>399</ymax>
    </bndbox>
    <confidence>0.060791</confidence>
  </object>
  <object>
    <name>Vehicle</name>
    <bndbox>
      <xmin>919</xmin>
      <ymin>528</ymin>
      <xmax>936</xmax>
      <ymax>558</ymax>
    </bndbox>
    <confidence>0.0650635</confidence>
  </object>
  <object>
    <name>Vehicle</name>
    <bndbox>
      <xmin>1459</xmin>
      <ymin>422</ymin>
      <xmax>1552</xmax>
      <ymax>468</ymax>
    </bndbox>
    <confidence>0.0805664</confidence>
  </object>
  <object>
    <name>Vehicle</name>
    <bndbox>
      <xmin>1694</xmin>
      <ymin>375</ymin>
      <xmax>1764</xmax>
      <ymax>439</ymax>
    </bndbox>
    <confidence>0.0993652</confidence>
  </object>
  <object>
    <name>Vehicle</name>
    <bndbox>
      <xmin>919</xmin>
      <ymin>528</ymin>
      <xmax>936</xmax>
      <ymax>558</ymax>
    </bndbox>
    <confidence>0.130859</confidence>
  </object>
  <object>
    <name>Vehicle</name>
    <bndbox>
      <xmin>853</xmin>
      <ymin>541</ymin>
      <xmax>879</xmax>
      <ymax>560</ymax>
    </bndbox>
    <confidence>0.25</confidence>
  </object>
  <object>
    <name>Vehicle</name>
    <bndbox>
      <xmin>1701</xmin>
      <ymin>374</ymin>
      <xmax>1759</xmax>
      <ymax>398</ymax>
    </bndbox>
    <confidence>0.293945</confidence>
  </object>
  <object>
    <name>TrafficSign</name>
    <bndbox>
      <xmin>1128</xmin>
      <ymin>442</ymin>
      <xmax>1148</xmax>
      <ymax>461</ymax>
    </bndbox>
    <confidence>0.343506</confidence>
  </object>
  <object>
    <name>Vehicle</name>
    <bndbox>
      <xmin>1459</xmin>
      <ymin>422</ymin>
      <xmax>1552</xmax>
      <ymax>468</ymax>
    </bndbox>
    <confidence>0.460693</confidence>
  </object>
  <object>
    <name>Vehicle</name>
    <bndbox>
      <xmin>1557</xmin>
      <ymin>377</ymin>
      <xmax>1752</xmax>
      <ymax>462</ymax>
    </bndbox>
    <confidence>0.879883</confidence>
  </object>
  <object>
    <name>Vehicle</name>
    <bndbox>
      <xmin>993</xmin>
      <ymin>510</ymin>
      <xmax>1027</xmax>
      <ymax>560</ymax>
    </bndbox>
    <confidence>0.902344</confidence>
  </object>
  <object>
    <name>Vehicle</name>
    <bndbox>
      <xmin>928</xmin>
      <ymin>511</ymin>
      <xmax>1011</xmax>
      <ymax>601</ymax>
    </bndbox>
    <confidence>0.936035</confidence>
  </object>
</annotation>
