<annotation>
  <object>
    <name>Vehicle</name>
    <bndbox>
      <xmin>388</xmin>
      <ymin>539</ymin>
      <xmax>467</xmax>
      <ymax>579</ymax>
    </bndbox>
    <confidence>0.0107117</confidence>
  </object>
  <object>
    <name>Vehicle</name>
    <bndbox>
      <xmin>261</xmin>
      <ymin>527</ymin>
      <xmax>341</xmax>
      <ymax>577</ymax>
    </bndbox>
    <confidence>0.0112381</confidence>
  </object>
  <object>
    <name>Vehicle</name>
    <bndbox>
      <xmin>1023</xmin>
      <ymin>545</ymin>
      <xmax>1045</xmax>
      <ymax>567</ymax>
    </bndbox>
    <confidence>0.0118561</confidence>
  </object>
  <object>
    <name>Vehicle</name>
    <bndbox>
      <xmin>1530</xmin>
      <ymin>557</ymin>
      <xmax>1582</xmax>
      <ymax>576</ymax>
    </bndbox>
    <confidence>0.0127182</confidence>
  </object>
  <object>
    <name>Vehicle</name>
    <bndbox>
      <xmin>1026</xmin>
      <ymin>546</ymin>
      <xmax>1047</xmax>
      <ymax>567</ymax>
    </bndbox>
    <confidence>0.0127411</confidence>
  </object>
  <object>
    <name>Vehicle</name>
    <bndbox>
      <xmin>1469</xmin>
      <ymin>554</ymin>
      <xmax>1509</xmax>
      <ymax>572</ymax>
    </bndbox>
    <confidence>0.0127716</confidence>
  </object>
  <object>
    <name>Vehicle</name>
    <bndbox>
      <xmin>480</xmin>
      <ymin>493</ymin>
      <xmax>623</xmax>
      <ymax>603</ymax>
    </bndbox>
    <confidence>0.0129318</confidence>
  </object>
  <object>
    <name>Vehicle</name>
    <bndbox>
      <xmin>0</xmin>
      <ymin>543</ymin>
      <xmax>16</xmax>
      <ymax>637</ymax>
    </bndbox>
    <confidence>0.014534</confidence>
  </object>
  <object>
    <name>Vehicle</name>
    <bndbox>
      <xmin>322</xmin>
      <ymin>519</ymin>
      <xmax>445</xmax>
      <ymax>546</ymax>
    </bndbox>
    <confidence>0.0152435</confidence>
  </object>
  <object>
    <name>Vehicle</name>
    <bndbox>
      <xmin>427</xmin>
      <ymin>543</ymin>
      <xmax>465</xmax>
      <ymax>582</ymax>
    </bndbox>
    <confidence>0.0214691</confidence>
  </object>
  <object>
    <name>Vehicle</name>
    <bndbox>
      <xmin>720</xmin>
      <ymin>539</ymin>
      <xmax>746</xmax>
      <ymax>569</ymax>
    </bndbox>
    <confidence>0.0267181</confidence>
  </object>
  <object>
    <name>Vehicle</name>
    <bndbox>
      <xmin>740</xmin>
      <ymin>527</ymin>
      <xmax>833</xmax>
      <ymax>593</ymax>
    </bndbox>
    <confidence>0.0377502</confidence>
  </object>
  <object>
    <name>Vehicle</name>
    <bndbox>
      <xmin>1025</xmin>
      <ymin>529</ymin>
      <xmax>1052</xmax>
      <ymax>557</ymax>
    </bndbox>
    <confidence>0.039978</confidence>
  </object>
  <object>
    <name>Vehicle</name>
    <bndbox>
      <xmin>1051</xmin>
      <ymin>528</ymin>
      <xmax>1072</xmax>
      <ymax>551</ymax>
    </bndbox>
    <confidence>0.0462341</confidence>
  </object>
  <object>
    <name>Vehicle</name>
    <bndbox>
      <xmin>1069</xmin>
      <ymin>528</ymin>
      <xmax>1095</xmax>
      <ymax>557</ymax>
    </bndbox>
    <confidence>0.0505676</confidence>
  </object>
  <object>
    <name>Vehicle</name>
    <bndbox>
      <xmin>0</xmin>
      <ymin>541</ymin>
      <xmax>42</xmax>
      <ymax>571</ymax>
    </bndbox>
    <confidence>0.0604858</confidence>
  </object>
  <object>
    <name>Vehicle</name>
    <bndbox>
      <xmin>624</xmin>
      <ymin>546</ymin>
      <xmax>650</xmax>
      <ymax>566</ymax>
    </bndbox>
    <confidence>0.0700684</confidence>
  </object>
  <object>
    <name>Vehicle</name>
    <bndbox>
      <xmin>714</xmin>
      <ymin>547</ymin>
      <xmax>742</xmax>
      <ymax>575</ymax>
    </bndbox>
    <confidence>0.088623</confidence>
  </object>
  <object>
    <name>Vehicle</name>
    <bndbox>
      <xmin>260</xmin>
      <ymin>518</ymin>
      <xmax>399</xmax>
      <ymax>573</ymax>
    </bndbox>
    <confidence>0.093689</confidence>
  </object>
  <object>
    <name>Vehicle</name>
    <bndbox>
      <xmin>1051</xmin>
      <ymin>528</ymin>
      <xmax>1072</xmax>
      <ymax>551</ymax>
    </bndbox>
    <confidence>0.119629</confidence>
  </object>
  <object>
    <name>Vehicle</name>
    <bndbox>
      <xmin>250</xmin>
      <ymin>536</ymin>
      <xmax>462</xmax>
      <ymax>626</ymax>
    </bndbox>
    <confidence>0.12146</confidence>
  </object>
  <object>
    <name>Vehicle</name>
    <bndbox>
      <xmin>0</xmin>
      <ymin>542</ymin>
      <xmax>36</xmax>
      <ymax>626</ymax>
    </bndbox>
    <confidence>0.123291</confidence>
  </object>
  <object>
    <name>Vehicle</name>
    <bndbox>
      <xmin>824</xmin>
      <ymin>532</ymin>
      <xmax>857</xmax>
      <ymax>561</ymax>
    </bndbox>
    <confidence>0.12915</confidence>
  </object>
  <object>
    <name>Vehicle</name>
    <bndbox>
      <xmin>824</xmin>
      <ymin>531</ymin>
      <xmax>857</xmax>
      <ymax>561</ymax>
    </bndbox>
    <confidence>0.134277</confidence>
  </object>
  <object>
    <name>Vehicle</name>
    <bndbox>
      <xmin>261</xmin>
      <ymin>527</ymin>
      <xmax>341</xmax>
      <ymax>577</ymax>
    </bndbox>
    <confidence>0.146484</confidence>
  </object>
  <object>
    <name>Vehicle</name>
    <bndbox>
      <xmin>1025</xmin>
      <ymin>531</ymin>
      <xmax>1050</xmax>
      <ymax>561</ymax>
    </bndbox>
    <confidence>0.179688</confidence>
  </object>
  <object>
    <name>TrafficLight</name>
    <bndbox>
      <xmin>1000</xmin>
      <ymin>488</ymin>
      <xmax>1015</xmax>
      <ymax>493</ymax>
    </bndbox>
    <confidence>0.19165</confidence>
  </object>
  <object>
    <name>Vehicle</name>
    <bndbox>
      <xmin>1068</xmin>
      <ymin>528</ymin>
      <xmax>1096</xmax>
      <ymax>557</ymax>
    </bndbox>
    <confidence>0.232056</confidence>
  </object>
  <object>
    <name>Vehicle</name>
    <bndbox>
      <xmin>869</xmin>
      <ymin>540</ymin>
      <xmax>894</xmax>
      <ymax>559</ymax>
    </bndbox>
    <confidence>0.235962</confidence>
  </object>
  <object>
    <name>Vehicle</name>
    <bndbox>
      <xmin>1023</xmin>
      <ymin>546</ymin>
      <xmax>1045</xmax>
      <ymax>568</ymax>
    </bndbox>
    <confidence>0.356689</confidence>
  </object>
  <object>
    <name>Vehicle</name>
    <bndbox>
      <xmin>956</xmin>
      <ymin>542</ymin>
      <xmax>978</xmax>
      <ymax>559</ymax>
    </bndbox>
    <confidence>0.386719</confidence>
  </object>
  <object>
    <name>Vehicle</name>
    <bndbox>
      <xmin>1025</xmin>
      <ymin>528</ymin>
      <xmax>1052</xmax>
      <ymax>555</ymax>
    </bndbox>
    <confidence>0.437988</confidence>
  </object>
  <object>
    <name>Vehicle</name>
    <bndbox>
      <xmin>609</xmin>
      <ymin>548</ymin>
      <xmax>650</xmax>
      <ymax>588</ymax>
    </bndbox>
    <confidence>0.505371</confidence>
  </object>
  <object>
    <name>Vehicle</name>
    <bndbox>
      <xmin>824</xmin>
      <ymin>532</ymin>
      <xmax>857</xmax>
      <ymax>561</ymax>
    </bndbox>
    <confidence>0.574219</confidence>
  </object>
  <object>
    <name>Vehicle</name>
    <bndbox>
      <xmin>261</xmin>
      <ymin>517</ymin>
      <xmax>395</xmax>
      <ymax>573</ymax>
    </bndbox>
    <confidence>0.634766</confidence>
  </object>
  <object>
    <name>Vehicle</name>
    <bndbox>
      <xmin>1069</xmin>
      <ymin>528</ymin>
      <xmax>1095</xmax>
      <ymax>557</ymax>
    </bndbox>
    <confidence>0.661133</confidence>
  </object>
  <object>
    <name>Vehicle</name>
    <bndbox>
      <xmin>457</xmin>
      <ymin>545</ymin>
      <xmax>487</xmax>
      <ymax>598</ymax>
    </bndbox>
    <confidence>0.751953</confidence>
  </object>
  <object>
    <name>Vehicle</name>
    <bndbox>
      <xmin>617</xmin>
      <ymin>538</ymin>
      <xmax>718</xmax>
      <ymax>587</ymax>
    </bndbox>
    <confidence>0.874023</confidence>
  </object>
  <object>
    <name>Vehicle</name>
    <bndbox>
      <xmin>740</xmin>
      <ymin>527</ymin>
      <xmax>833</xmax>
      <ymax>592</ymax>
    </bndbox>
    <confidence>0.929688</confidence>
  </object>
  <object>
    <name>Vehicle</name>
    <bndbox>
      <xmin>971</xmin>
      <ymin>542</ymin>
      <xmax>1037</xmax>
      <ymax>594</ymax>
    </bndbox>
    <confidence>0.929688</confidence>
  </object>
  <object>
    <name>Vehicle</name>
    <bndbox>
      <xmin>480</xmin>
      <ymin>493</ymin>
      <xmax>623</xmax>
      <ymax>603</ymax>
    </bndbox>
    <confidence>0.940918</confidence>
  </object>
  <object>
    <name>Vehicle</name>
    <bndbox>
      <xmin>247</xmin>
      <ymin>537</ymin>
      <xmax>462</xmax>
      <ymax>627</ymax>
    </bndbox>
    <confidence>0.941895</confidence>
  </object>
  <object>
    <name>Vehicle</name>
    <bndbox>
      <xmin>0</xmin>
      <ymin>531</ymin>
      <xmax>216</xmax>
      <ymax>659</ymax>
    </bndbox>
    <confidence>0.951172</confidence>
  </object>
</annotation>
