<annotation>
  <object>
    <name>TrafficLight</name>
    <bndbox>
      <xmin>656</xmin>
      <ymin>503</ymin>
      <xmax>666</xmax>
      <ymax>509</ymax>
    </bndbox>
    <confidence>0.0190582</confidence>
  </object>
  <object>
    <name>Vehicle</name>
    <bndbox>
      <xmin>852</xmin>
      <ymin>539</ymin>
      <xmax>870</xmax>
      <ymax>556</ymax>
    </bndbox>
    <confidence>0.0191956</confidence>
  </object>
  <object>
    <name>Vehicle</name>
    <bndbox>
      <xmin>1774</xmin>
      <ymin>594</ymin>
      <xmax>1897</xmax>
      <ymax>669</ymax>
    </bndbox>
    <confidence>0.0198822</confidence>
  </object>
  <object>
    <name>Vehicle</name>
    <bndbox>
      <xmin>1093</xmin>
      <ymin>576</ymin>
      <xmax>1128</xmax>
      <ymax>597</ymax>
    </bndbox>
    <confidence>0.0213623</confidence>
  </object>
  <object>
    <name>Vehicle</name>
    <bndbox>
      <xmin>1318</xmin>
      <ymin>623</ymin>
      <xmax>1381</xmax>
      <ymax>682</ymax>
    </bndbox>
    <confidence>0.0215912</confidence>
  </object>
  <object>
    <name>Vehicle</name>
    <bndbox>
      <xmin>1725</xmin>
      <ymin>528</ymin>
      <xmax>1770</xmax>
      <ymax>559</ymax>
    </bndbox>
    <confidence>0.0856323</confidence>
  </object>
  <object>
    <name>Vehicle</name>
    <bndbox>
      <xmin>1774</xmin>
      <ymin>594</ymin>
      <xmax>1897</xmax>
      <ymax>669</ymax>
    </bndbox>
    <confidence>0.313965</confidence>
  </object>
  <object>
    <name>TrafficSign</name>
    <bndbox>
      <xmin>706</xmin>
      <ymin>511</ymin>
      <xmax>726</xmax>
      <ymax>531</ymax>
    </bndbox>
    <confidence>0.550781</confidence>
  </object>
  <object>
    <name>Vehicle</name>
    <bndbox>
      <xmin>900</xmin>
      <ymin>538</ymin>
      <xmax>925</xmax>
      <ymax>560</ymax>
    </bndbox>
    <confidence>0.719727</confidence>
  </object>
  <object>
    <name>Vehicle</name>
    <bndbox>
      <xmin>932</xmin>
      <ymin>534</ymin>
      <xmax>971</xmax>
      <ymax>567</ymax>
    </bndbox>
    <confidence>0.908203</confidence>
  </object>
  <object>
    <name>Vehicle</name>
    <bndbox>
      <xmin>522</xmin>
      <ymin>535</ymin>
      <xmax>608</xmax>
      <ymax>588</ymax>
    </bndbox>
    <confidence>0.944824</confidence>
  </object>
</annotation>
