<annotation>
  <object>
    <name>Vehicle</name>
    <bndbox>
      <xmin>741</xmin>
      <ymin>520</ymin>
      <xmax>792</xmax>
      <ymax>542</ymax>
    </bndbox>
    <confidence>0.0108948</confidence>
  </object>
  <object>
    <name>Vehicle</name>
    <bndbox>
      <xmin>1101</xmin>
      <ymin>505</ymin>
      <xmax>1125</xmax>
      <ymax>533</ymax>
    </bndbox>
    <confidence>0.0130005</confidence>
  </object>
  <object>
    <name>Vehicle</name>
    <bndbox>
      <xmin>451</xmin>
      <ymin>532</ymin>
      <xmax>527</xmax>
      <ymax>569</ymax>
    </bndbox>
    <confidence>0.0132141</confidence>
  </object>
  <object>
    <name>TrafficLight</name>
    <bndbox>
      <xmin>780</xmin>
      <ymin>490</ymin>
      <xmax>793</xmax>
      <ymax>495</ymax>
    </bndbox>
    <confidence>0.0166473</confidence>
  </object>
  <object>
    <name>TrafficLight</name>
    <bndbox>
      <xmin>993</xmin>
      <ymin>470</ymin>
      <xmax>1011</xmax>
      <ymax>476</ymax>
    </bndbox>
    <confidence>0.0221252</confidence>
  </object>
  <object>
    <name>Vehicle</name>
    <bndbox>
      <xmin>700</xmin>
      <ymin>525</ymin>
      <xmax>730</xmax>
      <ymax>548</ymax>
    </bndbox>
    <confidence>0.0265045</confidence>
  </object>
  <object>
    <name>Vehicle</name>
    <bndbox>
      <xmin>850</xmin>
      <ymin>523</ymin>
      <xmax>882</xmax>
      <ymax>549</ymax>
    </bndbox>
    <confidence>0.0313721</confidence>
  </object>
  <object>
    <name>Vehicle</name>
    <bndbox>
      <xmin>813</xmin>
      <ymin>525</ymin>
      <xmax>843</xmax>
      <ymax>549</ymax>
    </bndbox>
    <confidence>0.0343323</confidence>
  </object>
  <object>
    <name>Vehicle</name>
    <bndbox>
      <xmin>699</xmin>
      <ymin>526</ymin>
      <xmax>730</xmax>
      <ymax>551</ymax>
    </bndbox>
    <confidence>0.0918579</confidence>
  </object>
  <object>
    <name>Vehicle</name>
    <bndbox>
      <xmin>991</xmin>
      <ymin>523</ymin>
      <xmax>1012</xmax>
      <ymax>539</ymax>
    </bndbox>
    <confidence>0.0927124</confidence>
  </object>
  <object>
    <name>Vehicle</name>
    <bndbox>
      <xmin>1063</xmin>
      <ymin>506</ymin>
      <xmax>1108</xmax>
      <ymax>540</ymax>
    </bndbox>
    <confidence>0.123535</confidence>
  </object>
  <object>
    <name>Vehicle</name>
    <bndbox>
      <xmin>672</xmin>
      <ymin>533</ymin>
      <xmax>732</xmax>
      <ymax>559</ymax>
    </bndbox>
    <confidence>0.154175</confidence>
  </object>
  <object>
    <name>Vehicle</name>
    <bndbox>
      <xmin>1101</xmin>
      <ymin>505</ymin>
      <xmax>1125</xmax>
      <ymax>533</ymax>
    </bndbox>
    <confidence>0.15918</confidence>
  </object>
  <object>
    <name>TrafficSign</name>
    <bndbox>
      <xmin>944</xmin>
      <ymin>697</ymin>
      <xmax>1066</xmax>
      <ymax>775</ymax>
    </bndbox>
    <confidence>0.185791</confidence>
  </object>
  <object>
    <name>Vehicle</name>
    <bndbox>
      <xmin>871</xmin>
      <ymin>522</ymin>
      <xmax>892</xmax>
      <ymax>546</ymax>
    </bndbox>
    <confidence>0.263672</confidence>
  </object>
  <object>
    <name>Vehicle</name>
    <bndbox>
      <xmin>700</xmin>
      <ymin>525</ymin>
      <xmax>730</xmax>
      <ymax>548</ymax>
    </bndbox>
    <confidence>0.369629</confidence>
  </object>
  <object>
    <name>Vehicle</name>
    <bndbox>
      <xmin>811</xmin>
      <ymin>524</ymin>
      <xmax>844</xmax>
      <ymax>549</ymax>
    </bndbox>
    <confidence>0.772461</confidence>
  </object>
  <object>
    <name>Vehicle</name>
    <bndbox>
      <xmin>906</xmin>
      <ymin>523</ymin>
      <xmax>932</xmax>
      <ymax>545</ymax>
    </bndbox>
    <confidence>0.772949</confidence>
  </object>
  <object>
    <name>Vehicle</name>
    <bndbox>
      <xmin>670</xmin>
      <ymin>534</ymin>
      <xmax>730</xmax>
      <ymax>560</ymax>
    </bndbox>
    <confidence>0.788086</confidence>
  </object>
  <object>
    <name>Vehicle</name>
    <bndbox>
      <xmin>1021</xmin>
      <ymin>526</ymin>
      <xmax>1054</xmax>
      <ymax>553</ymax>
    </bndbox>
    <confidence>0.878418</confidence>
  </object>
  <object>
    <name>Vehicle</name>
    <bndbox>
      <xmin>850</xmin>
      <ymin>523</ymin>
      <xmax>882</xmax>
      <ymax>549</ymax>
    </bndbox>
    <confidence>0.879395</confidence>
  </object>
  <object>
    <name>Vehicle</name>
    <bndbox>
      <xmin>948</xmin>
      <ymin>524</ymin>
      <xmax>983</xmax>
      <ymax>551</ymax>
    </bndbox>
    <confidence>0.881836</confidence>
  </object>
  <object>
    <name>Vehicle</name>
    <bndbox>
      <xmin>620</xmin>
      <ymin>541</ymin>
      <xmax>672</xmax>
      <ymax>568</ymax>
    </bndbox>
    <confidence>0.883789</confidence>
  </object>
  <object>
    <name>Vehicle</name>
    <bndbox>
      <xmin>1065</xmin>
      <ymin>505</ymin>
      <xmax>1108</xmax>
      <ymax>538</ymax>
    </bndbox>
    <confidence>0.901855</confidence>
  </object>
  <object>
    <name>Vehicle</name>
    <bndbox>
      <xmin>377</xmin>
      <ymin>544</ymin>
      <xmax>450</xmax>
      <ymax>601</ymax>
    </bndbox>
    <confidence>0.902344</confidence>
  </object>
  <object>
    <name>Vehicle</name>
    <bndbox>
      <xmin>208</xmin>
      <ymin>536</ymin>
      <xmax>383</xmax>
      <ymax>630</ymax>
    </bndbox>
    <confidence>0.949707</confidence>
  </object>
  <object>
    <name>Vehicle</name>
    <bndbox>
      <xmin>1123</xmin>
      <ymin>502</ymin>
      <xmax>1305</xmax>
      <ymax>630</ymax>
    </bndbox>
    <confidence>0.955566</confidence>
  </object>
</annotation>
