<annotation>
  <object>
    <name>Vehicle</name>
    <bndbox>
      <xmin>1151</xmin>
      <ymin>505</ymin>
      <xmax>1167</xmax>
      <ymax>554</ymax>
    </bndbox>
    <confidence>0.0142975</confidence>
  </object>
  <object>
    <name>Vehicle</name>
    <bndbox>
      <xmin>988</xmin>
      <ymin>513</ymin>
      <xmax>1030</xmax>
      <ymax>548</ymax>
    </bndbox>
    <confidence>0.0169373</confidence>
  </object>
  <object>
    <name>Vehicle</name>
    <bndbox>
      <xmin>1051</xmin>
      <ymin>491</ymin>
      <xmax>1115</xmax>
      <ymax>524</ymax>
    </bndbox>
    <confidence>0.0180206</confidence>
  </object>
  <object>
    <name>Vehicle</name>
    <bndbox>
      <xmin>988</xmin>
      <ymin>513</ymin>
      <xmax>1030</xmax>
      <ymax>548</ymax>
    </bndbox>
    <confidence>0.0185699</confidence>
  </object>
  <object>
    <name>Vehicle</name>
    <bndbox>
      <xmin>928</xmin>
      <ymin>531</ymin>
      <xmax>1015</xmax>
      <ymax>598</ymax>
    </bndbox>
    <confidence>0.022934</confidence>
  </object>
  <object>
    <name>Vehicle</name>
    <bndbox>
      <xmin>1048</xmin>
      <ymin>494</ymin>
      <xmax>1116</xmax>
      <ymax>569</ymax>
    </bndbox>
    <confidence>0.0238037</confidence>
  </object>
  <object>
    <name>Vehicle</name>
    <bndbox>
      <xmin>1041</xmin>
      <ymin>498</ymin>
      <xmax>1111</xmax>
      <ymax>571</ymax>
    </bndbox>
    <confidence>0.0303345</confidence>
  </object>
  <object>
    <name>Vehicle</name>
    <bndbox>
      <xmin>1118</xmin>
      <ymin>510</ymin>
      <xmax>1161</xmax>
      <ymax>554</ymax>
    </bndbox>
    <confidence>0.0322876</confidence>
  </object>
  <object>
    <name>Vehicle</name>
    <bndbox>
      <xmin>1139</xmin>
      <ymin>504</ymin>
      <xmax>1172</xmax>
      <ymax>562</ymax>
    </bndbox>
    <confidence>0.0331726</confidence>
  </object>
  <object>
    <name>Vehicle</name>
    <bndbox>
      <xmin>1028</xmin>
      <ymin>516</ymin>
      <xmax>1051</xmax>
      <ymax>547</ymax>
    </bndbox>
    <confidence>0.0458679</confidence>
  </object>
  <object>
    <name>Vehicle</name>
    <bndbox>
      <xmin>1152</xmin>
      <ymin>471</ymin>
      <xmax>1185</xmax>
      <ymax>567</ymax>
    </bndbox>
    <confidence>0.107483</confidence>
  </object>
  <object>
    <name>Vehicle</name>
    <bndbox>
      <xmin>1038</xmin>
      <ymin>534</ymin>
      <xmax>1098</xmax>
      <ymax>578</ymax>
    </bndbox>
    <confidence>0.26709</confidence>
  </object>
  <object>
    <name>Vehicle</name>
    <bndbox>
      <xmin>928</xmin>
      <ymin>531</ymin>
      <xmax>1015</xmax>
      <ymax>598</ymax>
    </bndbox>
    <confidence>0.455078</confidence>
  </object>
  <object>
    <name>Vehicle</name>
    <bndbox>
      <xmin>1046</xmin>
      <ymin>492</ymin>
      <xmax>1118</xmax>
      <ymax>568</ymax>
    </bndbox>
    <confidence>0.655762</confidence>
  </object>
  <object>
    <name>Vehicle</name>
    <bndbox>
      <xmin>988</xmin>
      <ymin>513</ymin>
      <xmax>1030</xmax>
      <ymax>547</ymax>
    </bndbox>
    <confidence>0.84668</confidence>
  </object>
  <object>
    <name>Vehicle</name>
    <bndbox>
      <xmin>1036</xmin>
      <ymin>534</ymin>
      <xmax>1099</xmax>
      <ymax>578</ymax>
    </bndbox>
    <confidence>0.907715</confidence>
  </object>
  <object>
    <name>Vehicle</name>
    <bndbox>
      <xmin>928</xmin>
      <ymin>532</ymin>
      <xmax>1015</xmax>
      <ymax>597</ymax>
    </bndbox>
    <confidence>0.932617</confidence>
  </object>
  <object>
    <name>Vehicle</name>
    <bndbox>
      <xmin>1161</xmin>
      <ymin>368</ymin>
      <xmax>1483</xmax>
      <ymax>611</ymax>
    </bndbox>
    <confidence>0.95752</confidence>
  </object>
</annotation>
