<annotation>
  <object>
    <name>Vehicle</name>
    <bndbox>
      <xmin>1818</xmin>
      <ymin>523</ymin>
      <xmax>1870</xmax>
      <ymax>550</ymax>
    </bndbox>
    <confidence>0.0120087</confidence>
  </object>
  <object>
    <name>Vehicle</name>
    <bndbox>
      <xmin>988</xmin>
      <ymin>519</ymin>
      <xmax>1008</xmax>
      <ymax>544</ymax>
    </bndbox>
    <confidence>0.0120316</confidence>
  </object>
  <object>
    <name>Pedestrian</name>
    <bndbox>
      <xmin>1731</xmin>
      <ymin>519</ymin>
      <xmax>1744</xmax>
      <ymax>547</ymax>
    </bndbox>
    <confidence>0.0166473</confidence>
  </object>
  <object>
    <name>Vehicle</name>
    <bndbox>
      <xmin>964</xmin>
      <ymin>524</ymin>
      <xmax>988</xmax>
      <ymax>547</ymax>
    </bndbox>
    <confidence>0.0188751</confidence>
  </object>
  <object>
    <name>Vehicle</name>
    <bndbox>
      <xmin>963</xmin>
      <ymin>529</ymin>
      <xmax>985</xmax>
      <ymax>548</ymax>
    </bndbox>
    <confidence>0.0247192</confidence>
  </object>
  <object>
    <name>Vehicle</name>
    <bndbox>
      <xmin>984</xmin>
      <ymin>521</ymin>
      <xmax>1008</xmax>
      <ymax>544</ymax>
    </bndbox>
    <confidence>0.0559998</confidence>
  </object>
  <object>
    <name>Vehicle</name>
    <bndbox>
      <xmin>1818</xmin>
      <ymin>523</ymin>
      <xmax>1875</xmax>
      <ymax>550</ymax>
    </bndbox>
    <confidence>0.0942383</confidence>
  </object>
  <object>
    <name>Vehicle</name>
    <bndbox>
      <xmin>1001</xmin>
      <ymin>530</ymin>
      <xmax>1029</xmax>
      <ymax>553</ymax>
    </bndbox>
    <confidence>0.164185</confidence>
  </object>
  <object>
    <name>Vehicle</name>
    <bndbox>
      <xmin>988</xmin>
      <ymin>519</ymin>
      <xmax>1008</xmax>
      <ymax>544</ymax>
    </bndbox>
    <confidence>0.208862</confidence>
  </object>
  <object>
    <name>Vehicle</name>
    <bndbox>
      <xmin>963</xmin>
      <ymin>529</ymin>
      <xmax>984</xmax>
      <ymax>548</ymax>
    </bndbox>
    <confidence>0.498047</confidence>
  </object>
  <object>
    <name>Vehicle</name>
    <bndbox>
      <xmin>1001</xmin>
      <ymin>530</ymin>
      <xmax>1029</xmax>
      <ymax>553</ymax>
    </bndbox>
    <confidence>0.864746</confidence>
  </object>
  <object>
    <name>Vehicle</name>
    <bndbox>
      <xmin>81</xmin>
      <ymin>481</ymin>
      <xmax>275</xmax>
      <ymax>536</ymax>
    </bndbox>
    <confidence>0.864746</confidence>
  </object>
  <object>
    <name>Vehicle</name>
    <bndbox>
      <xmin>897</xmin>
      <ymin>532</ymin>
      <xmax>923</xmax>
      <ymax>555</ymax>
    </bndbox>
    <confidence>0.867188</confidence>
  </object>
  <object>
    <name>Vehicle</name>
    <bndbox>
      <xmin>915</xmin>
      <ymin>532</ymin>
      <xmax>969</xmax>
      <ymax>571</ymax>
    </bndbox>
    <confidence>0.916992</confidence>
  </object>
  <object>
    <name>Vehicle</name>
    <bndbox>
      <xmin>1034</xmin>
      <ymin>499</ymin>
      <xmax>1176</xmax>
      <ymax>621</ymax>
    </bndbox>
    <confidence>0.943848</confidence>
  </object>
  <object>
    <name>Vehicle</name>
    <bndbox>
      <xmin>1210</xmin>
      <ymin>530</ymin>
      <xmax>1354</xmax>
      <ymax>613</ymax>
    </bndbox>
    <confidence>0.973633</confidence>
  </object>
</annotation>
