<annotation>
  <object>
    <name>Vehicle</name>
    <bndbox>
      <xmin>91</xmin>
      <ymin>514</ymin>
      <xmax>274</xmax>
      <ymax>548</ymax>
    </bndbox>
    <confidence>0.0111771</confidence>
  </object>
  <object>
    <name>Vehicle</name>
    <bndbox>
      <xmin>1060</xmin>
      <ymin>528</ymin>
      <xmax>1091</xmax>
      <ymax>562</ymax>
    </bndbox>
    <confidence>0.0119324</confidence>
  </object>
  <object>
    <name>Vehicle</name>
    <bndbox>
      <xmin>954</xmin>
      <ymin>523</ymin>
      <xmax>1038</xmax>
      <ymax>596</ymax>
    </bndbox>
    <confidence>0.012085</confidence>
  </object>
  <object>
    <name>Vehicle</name>
    <bndbox>
      <xmin>1066</xmin>
      <ymin>518</ymin>
      <xmax>1097</xmax>
      <ymax>540</ymax>
    </bndbox>
    <confidence>0.0121384</confidence>
  </object>
  <object>
    <name>Vehicle</name>
    <bndbox>
      <xmin>0</xmin>
      <ymin>517</ymin>
      <xmax>70</xmax>
      <ymax>557</ymax>
    </bndbox>
    <confidence>0.0121613</confidence>
  </object>
  <object>
    <name>Vehicle</name>
    <bndbox>
      <xmin>74</xmin>
      <ymin>506</ymin>
      <xmax>221</xmax>
      <ymax>551</ymax>
    </bndbox>
    <confidence>0.0124435</confidence>
  </object>
  <object>
    <name>Vehicle</name>
    <bndbox>
      <xmin>0</xmin>
      <ymin>515</ymin>
      <xmax>66</xmax>
      <ymax>550</ymax>
    </bndbox>
    <confidence>0.0129547</confidence>
  </object>
  <object>
    <name>Vehicle</name>
    <bndbox>
      <xmin>1062</xmin>
      <ymin>528</ymin>
      <xmax>1092</xmax>
      <ymax>562</ymax>
    </bndbox>
    <confidence>0.013588</confidence>
  </object>
  <object>
    <name>Vehicle</name>
    <bndbox>
      <xmin>0</xmin>
      <ymin>510</ymin>
      <xmax>126</xmax>
      <ymax>553</ymax>
    </bndbox>
    <confidence>0.019455</confidence>
  </object>
  <object>
    <name>Vehicle</name>
    <bndbox>
      <xmin>70</xmin>
      <ymin>507</ymin>
      <xmax>259</xmax>
      <ymax>551</ymax>
    </bndbox>
    <confidence>0.0202789</confidence>
  </object>
  <object>
    <name>Vehicle</name>
    <bndbox>
      <xmin>1078</xmin>
      <ymin>537</ymin>
      <xmax>1150</xmax>
      <ymax>587</ymax>
    </bndbox>
    <confidence>0.0205231</confidence>
  </object>
  <object>
    <name>Vehicle</name>
    <bndbox>
      <xmin>1066</xmin>
      <ymin>518</ymin>
      <xmax>1097</xmax>
      <ymax>539</ymax>
    </bndbox>
    <confidence>0.0229034</confidence>
  </object>
  <object>
    <name>Vehicle</name>
    <bndbox>
      <xmin>959</xmin>
      <ymin>515</ymin>
      <xmax>996</xmax>
      <ymax>539</ymax>
    </bndbox>
    <confidence>0.0248871</confidence>
  </object>
  <object>
    <name>Vehicle</name>
    <bndbox>
      <xmin>629</xmin>
      <ymin>509</ymin>
      <xmax>676</xmax>
      <ymax>528</ymax>
    </bndbox>
    <confidence>0.035614</confidence>
  </object>
  <object>
    <name>Vehicle</name>
    <bndbox>
      <xmin>959</xmin>
      <ymin>515</ymin>
      <xmax>996</xmax>
      <ymax>539</ymax>
    </bndbox>
    <confidence>0.123535</confidence>
  </object>
  <object>
    <name>Vehicle</name>
    <bndbox>
      <xmin>631</xmin>
      <ymin>508</ymin>
      <xmax>724</xmax>
      <ymax>528</ymax>
    </bndbox>
    <confidence>0.128052</confidence>
  </object>
  <object>
    <name>Vehicle</name>
    <bndbox>
      <xmin>820</xmin>
      <ymin>530</ymin>
      <xmax>839</xmax>
      <ymax>565</ymax>
    </bndbox>
    <confidence>0.182739</confidence>
  </object>
  <object>
    <name>Vehicle</name>
    <bndbox>
      <xmin>960</xmin>
      <ymin>514</ymin>
      <xmax>995</xmax>
      <ymax>538</ymax>
    </bndbox>
    <confidence>0.188477</confidence>
  </object>
  <object>
    <name>Vehicle</name>
    <bndbox>
      <xmin>73</xmin>
      <ymin>506</ymin>
      <xmax>160</xmax>
      <ymax>550</ymax>
    </bndbox>
    <confidence>0.192261</confidence>
  </object>
  <object>
    <name>Vehicle</name>
    <bndbox>
      <xmin>1060</xmin>
      <ymin>528</ymin>
      <xmax>1091</xmax>
      <ymax>562</ymax>
    </bndbox>
    <confidence>0.841797</confidence>
  </object>
  <object>
    <name>Vehicle</name>
    <bndbox>
      <xmin>795</xmin>
      <ymin>530</ymin>
      <xmax>829</xmax>
      <ymax>573</ymax>
    </bndbox>
    <confidence>0.886719</confidence>
  </object>
  <object>
    <name>Vehicle</name>
    <bndbox>
      <xmin>931</xmin>
      <ymin>530</ymin>
      <xmax>961</xmax>
      <ymax>560</ymax>
    </bndbox>
    <confidence>0.890625</confidence>
  </object>
  <object>
    <name>Vehicle</name>
    <bndbox>
      <xmin>730</xmin>
      <ymin>521</ymin>
      <xmax>807</xmax>
      <ymax>592</ymax>
    </bndbox>
    <confidence>0.931152</confidence>
  </object>
  <object>
    <name>Vehicle</name>
    <bndbox>
      <xmin>836</xmin>
      <ymin>458</ymin>
      <xmax>939</xmax>
      <ymax>580</ymax>
    </bndbox>
    <confidence>0.938477</confidence>
  </object>
  <object>
    <name>Vehicle</name>
    <bndbox>
      <xmin>1078</xmin>
      <ymin>536</ymin>
      <xmax>1150</xmax>
      <ymax>587</ymax>
    </bndbox>
    <confidence>0.942383</confidence>
  </object>
  <object>
    <name>Vehicle</name>
    <bndbox>
      <xmin>953</xmin>
      <ymin>522</ymin>
      <xmax>1038</xmax>
      <ymax>596</ymax>
    </bndbox>
    <confidence>0.942871</confidence>
  </object>
  <object>
    <name>Vehicle</name>
    <bndbox>
      <xmin>509</xmin>
      <ymin>526</ymin>
      <xmax>622</xmax>
      <ymax>609</ymax>
    </bndbox>
    <confidence>0.949707</confidence>
  </object>
  <object>
    <name>Vehicle</name>
    <bndbox>
      <xmin>43</xmin>
      <ymin>520</ymin>
      <xmax>397</xmax>
      <ymax>698</ymax>
    </bndbox>
    <confidence>0.958984</confidence>
  </object>
  <object>
    <name>Vehicle</name>
    <bndbox>
      <xmin>589</xmin>
      <ymin>523</ymin>
      <xmax>790</xmax>
      <ymax>650</ymax>
    </bndbox>
    <confidence>0.961914</confidence>
  </object>
</annotation>
