<annotation>
  <object>
    <name>Vehicle</name>
    <bndbox>
      <xmin>1115</xmin>
      <ymin>537</ymin>
      <xmax>1137</xmax>
      <ymax>578</ymax>
    </bndbox>
    <confidence>0.0109329</confidence>
  </object>
  <object>
    <name>Vehicle</name>
    <bndbox>
      <xmin>1667</xmin>
      <ymin>513</ymin>
      <xmax>1737</xmax>
      <ymax>557</ymax>
    </bndbox>
    <confidence>0.0113907</confidence>
  </object>
  <object>
    <name>Pedestrian</name>
    <bndbox>
      <xmin>987</xmin>
      <ymin>521</ymin>
      <xmax>1001</xmax>
      <ymax>554</ymax>
    </bndbox>
    <confidence>0.0118866</confidence>
  </object>
  <object>
    <name>Vehicle</name>
    <bndbox>
      <xmin>629</xmin>
      <ymin>377</ymin>
      <xmax>673</xmax>
      <ymax>420</ymax>
    </bndbox>
    <confidence>0.0124207</confidence>
  </object>
  <object>
    <name>Pedestrian</name>
    <bndbox>
      <xmin>1389</xmin>
      <ymin>508</ymin>
      <xmax>1399</xmax>
      <ymax>559</ymax>
    </bndbox>
    <confidence>0.0132446</confidence>
  </object>
  <object>
    <name>Vehicle</name>
    <bndbox>
      <xmin>81</xmin>
      <ymin>457</ymin>
      <xmax>249</xmax>
      <ymax>525</ymax>
    </bndbox>
    <confidence>0.0150223</confidence>
  </object>
  <object>
    <name>Vehicle</name>
    <bndbox>
      <xmin>112</xmin>
      <ymin>559</ymin>
      <xmax>229</xmax>
      <ymax>592</ymax>
    </bndbox>
    <confidence>0.0158081</confidence>
  </object>
  <object>
    <name>Vehicle</name>
    <bndbox>
      <xmin>846</xmin>
      <ymin>498</ymin>
      <xmax>946</xmax>
      <ymax>621</ymax>
    </bndbox>
    <confidence>0.0180511</confidence>
  </object>
  <object>
    <name>Vehicle</name>
    <bndbox>
      <xmin>0</xmin>
      <ymin>420</ymin>
      <xmax>145</xmax>
      <ymax>527</ymax>
    </bndbox>
    <confidence>0.0182037</confidence>
  </object>
  <object>
    <name>Vehicle</name>
    <bndbox>
      <xmin>690</xmin>
      <ymin>393</ymin>
      <xmax>725</xmax>
      <ymax>416</ymax>
    </bndbox>
    <confidence>0.0189056</confidence>
  </object>
  <object>
    <name>Vehicle</name>
    <bndbox>
      <xmin>81</xmin>
      <ymin>454</ymin>
      <xmax>145</xmax>
      <ymax>525</ymax>
    </bndbox>
    <confidence>0.0211182</confidence>
  </object>
  <object>
    <name>Pedestrian</name>
    <bndbox>
      <xmin>1390</xmin>
      <ymin>507</ymin>
      <xmax>1408</xmax>
      <ymax>562</ymax>
    </bndbox>
    <confidence>0.0211334</confidence>
  </object>
  <object>
    <name>Vehicle</name>
    <bndbox>
      <xmin>0</xmin>
      <ymin>468</ymin>
      <xmax>36</xmax>
      <ymax>533</ymax>
    </bndbox>
    <confidence>0.0227814</confidence>
  </object>
  <object>
    <name>Vehicle</name>
    <bndbox>
      <xmin>0</xmin>
      <ymin>468</ymin>
      <xmax>36</xmax>
      <ymax>533</ymax>
    </bndbox>
    <confidence>0.0238647</confidence>
  </object>
  <object>
    <name>Pedestrian</name>
    <bndbox>
      <xmin>1115</xmin>
      <ymin>537</ymin>
      <xmax>1140</xmax>
      <ymax>578</ymax>
    </bndbox>
    <confidence>0.0239868</confidence>
  </object>
  <object>
    <name>Vehicle</name>
    <bndbox>
      <xmin>806</xmin>
      <ymin>538</ymin>
      <xmax>823</xmax>
      <ymax>572</ymax>
    </bndbox>
    <confidence>0.0283661</confidence>
  </object>
  <object>
    <name>Vehicle</name>
    <bndbox>
      <xmin>1689</xmin>
      <ymin>513</ymin>
      <xmax>1737</xmax>
      <ymax>553</ymax>
    </bndbox>
    <confidence>0.0317688</confidence>
  </object>
  <object>
    <name>Pedestrian</name>
    <bndbox>
      <xmin>995</xmin>
      <ymin>527</ymin>
      <xmax>1005</xmax>
      <ymax>560</ymax>
    </bndbox>
    <confidence>0.0481262</confidence>
  </object>
  <object>
    <name>Vehicle</name>
    <bndbox>
      <xmin>1621</xmin>
      <ymin>488</ymin>
      <xmax>1659</xmax>
      <ymax>602</ymax>
    </bndbox>
    <confidence>0.0809937</confidence>
  </object>
  <object>
    <name>Pedestrian</name>
    <bndbox>
      <xmin>942</xmin>
      <ymin>537</ymin>
      <xmax>978</xmax>
      <ymax>577</ymax>
    </bndbox>
    <confidence>0.0884399</confidence>
  </object>
  <object>
    <name>Vehicle</name>
    <bndbox>
      <xmin>1691</xmin>
      <ymin>513</ymin>
      <xmax>1737</xmax>
      <ymax>548</ymax>
    </bndbox>
    <confidence>0.11792</confidence>
  </object>
  <object>
    <name>Pedestrian</name>
    <bndbox>
      <xmin>970</xmin>
      <ymin>530</ymin>
      <xmax>980</xmax>
      <ymax>559</ymax>
    </bndbox>
    <confidence>0.166138</confidence>
  </object>
  <object>
    <name>Vehicle</name>
    <bndbox>
      <xmin>819</xmin>
      <ymin>533</ymin>
      <xmax>851</xmax>
      <ymax>578</ymax>
    </bndbox>
    <confidence>0.183105</confidence>
  </object>
  <object>
    <name>Pedestrian</name>
    <bndbox>
      <xmin>1011</xmin>
      <ymin>523</ymin>
      <xmax>1026</xmax>
      <ymax>562</ymax>
    </bndbox>
    <confidence>0.251465</confidence>
  </object>
  <object>
    <name>Pedestrian</name>
    <bndbox>
      <xmin>1016</xmin>
      <ymin>521</ymin>
      <xmax>1030</xmax>
      <ymax>556</ymax>
    </bndbox>
    <confidence>0.29126</confidence>
  </object>
  <object>
    <name>Vehicle</name>
    <bndbox>
      <xmin>0</xmin>
      <ymin>555</ymin>
      <xmax>114</xmax>
      <ymax>600</ymax>
    </bndbox>
    <confidence>0.292969</confidence>
  </object>
  <object>
    <name>Vehicle</name>
    <bndbox>
      <xmin>846</xmin>
      <ymin>498</ymin>
      <xmax>946</xmax>
      <ymax>621</ymax>
    </bndbox>
    <confidence>0.307617</confidence>
  </object>
  <object>
    <name>Pedestrian</name>
    <bndbox>
      <xmin>1004</xmin>
      <ymin>525</ymin>
      <xmax>1014</xmax>
      <ymax>564</ymax>
    </bndbox>
    <confidence>0.466064</confidence>
  </object>
  <object>
    <name>Vehicle</name>
    <bndbox>
      <xmin>1669</xmin>
      <ymin>512</ymin>
      <xmax>1750</xmax>
      <ymax>557</ymax>
    </bndbox>
    <confidence>0.574707</confidence>
  </object>
  <object>
    <name>Vehicle</name>
    <bndbox>
      <xmin>809</xmin>
      <ymin>537</ymin>
      <xmax>838</xmax>
      <ymax>573</ymax>
    </bndbox>
    <confidence>0.770996</confidence>
  </object>
  <object>
    <name>Vehicle</name>
    <bndbox>
      <xmin>832</xmin>
      <ymin>527</ymin>
      <xmax>856</xmax>
      <ymax>582</ymax>
    </bndbox>
    <confidence>0.82373</confidence>
  </object>
  <object>
    <name>Vehicle</name>
    <bndbox>
      <xmin>847</xmin>
      <ymin>498</ymin>
      <xmax>945</xmax>
      <ymax>622</ymax>
    </bndbox>
    <confidence>0.865234</confidence>
  </object>
  <object>
    <name>Vehicle</name>
    <bndbox>
      <xmin>942</xmin>
      <ymin>537</ymin>
      <xmax>978</xmax>
      <ymax>577</ymax>
    </bndbox>
    <confidence>0.897461</confidence>
  </object>
  <object>
    <name>Pedestrian</name>
    <bndbox>
      <xmin>1624</xmin>
      <ymin>488</ymin>
      <xmax>1659</xmax>
      <ymax>602</ymax>
    </bndbox>
    <confidence>0.908203</confidence>
  </object>
  <object>
    <name>TrafficSign</name>
    <bndbox>
      <xmin>608</xmin>
      <ymin>127</ymin>
      <xmax>651</xmax>
      <ymax>169</ymax>
    </bndbox>
    <confidence>0.931641</confidence>
  </object>
</annotation>
