<annotation>
  <object>
    <name>Vehicle</name>
    <bndbox>
      <xmin>1036</xmin>
      <ymin>490</ymin>
      <xmax>1075</xmax>
      <ymax>549</ymax>
    </bndbox>
    <confidence>0.0133362</confidence>
  </object>
  <object>
    <name>Vehicle</name>
    <bndbox>
      <xmin>1045</xmin>
      <ymin>488</ymin>
      <xmax>1078</xmax>
      <ymax>524</ymax>
    </bndbox>
    <confidence>0.0516052</confidence>
  </object>
  <object>
    <name>Vehicle</name>
    <bndbox>
      <xmin>642</xmin>
      <ymin>530</ymin>
      <xmax>716</xmax>
      <ymax>558</ymax>
    </bndbox>
    <confidence>0.185913</confidence>
  </object>
  <object>
    <name>Vehicle</name>
    <bndbox>
      <xmin>921</xmin>
      <ymin>538</ymin>
      <xmax>945</xmax>
      <ymax>557</ymax>
    </bndbox>
    <confidence>0.628906</confidence>
  </object>
  <object>
    <name>Vehicle</name>
    <bndbox>
      <xmin>968</xmin>
      <ymin>528</ymin>
      <xmax>991</xmax>
      <ymax>556</ymax>
    </bndbox>
    <confidence>0.634277</confidence>
  </object>
  <object>
    <name>Vehicle</name>
    <bndbox>
      <xmin>1005</xmin>
      <ymin>493</ymin>
      <xmax>1067</xmax>
      <ymax>567</ymax>
    </bndbox>
    <confidence>0.925293</confidence>
  </object>
  <object>
    <name>Vehicle</name>
    <bndbox>
      <xmin>878</xmin>
      <ymin>531</ymin>
      <xmax>923</xmax>
      <ymax>567</ymax>
    </bndbox>
    <confidence>0.932129</confidence>
  </object>
</annotation>
